{
  "uuid": "427a35bb-913e-4b9b-899f-0a027206f242",
  "shortName": "stamp",
  "longName": "stamp",
  "companyName": "MakeAwesomeHappen",
  "versionCode": 1,
  "versionLabel": "1.0.0",
  "watchapp": {
    "watchface": false
  },
  "appKeys": {
    "dummy": 0
  },
  "resources": {
    "media": [
        {
            "name": "SETTINGS_ICON",
            "file": "img/settings.png",
            "type": "png"
        },
        {
            "name": "CLOCK_ICON",
            "file": "img/clock.png",
            "type": "png"
        },
        {
            "name": "EDIT_ICON",
            "file": "img/edit.png",
            "type": "png"
        },
        {
            "name": "BACK_IMAGE",
            "file": "img/back.png",
            "type": "png"
        }
    ]
  }
}
